[
  {
    "date": "2026-06-26",
    "home_team": "Detroit Tigers",
    "away_team": "Houston Astros",
    "predicted_winner": "Detroit Tigers",
    "win_probability": 0.6563119697191913,
    "model1_probability": 0.5888001844935751,
    "model2_probability": 0.6409982210938517,
    "model3_probability": 0.6759357452392578,
    "ensemble_probability": 0.6563119697191913,
    "start_time_et": "2026-06-26 18:40:00 EDT",
    "start_time": "2026-06-26T18:40:00-04:00",
    "venue_name": "Comerica Park",
    "day_night": "night",
    "model4_probability": 0.5381131527000329,
    "model5_probability": 0.7166638525378892,
    "model6_probability": 0.7906866073608398,
    "model7_probability": 0.6563119697191913,
    "model8_probability": 0.79265927566374,
    "model9_probability": 0.6731749176979065,
    "model_rf_probability": 0.5498937885658108,
    "model_nn_probability": 0.9832216095025365,
    "model_svm_probability": 0.5280095528245063,
    "model_advanced_catboost_basic_probability": 0.5433100529336156,
    "model_advanced_catboost_probability": 0.7712447250871206,
    "model_advanced_lgbm_basic_probability": 0.679537971215534,
    "model_advanced_lgbm_probability": 0.8479344734087546,
    "model_advanced_nn_probability": 0.049261989307222476,
    "model_advanced_rf_probability": 0.5613142448248578,
    "model_advanced_svm_probability": 0.5133837821409224,
    "model_advanced_xgboost_basic_probability": 0.7356476783752441,
    "model_advanced_xgboost_probability": 0.8901482820510864,
    "model1_extended_lgbm_probability": 0.5647855901144959,
    "model2_extended_catboost_probability": 0.5972416061345633,
    "model3_extended_xgboost_probability": 0.7959142327308655,
    "home_team_odds": -112.0,
    "home_team_probability_odds": 0.5283018868,
    "away_team_odds": -104.0,
    "away_team_probability_odds": 0.5098039216,
    "predicted_winner_odds": -112.0,
    "predicted_winner_probability_odds": 0.5283018868,
    "bookmaker": "fanduel",
    "bookmaker_title": "FanDuel"
  },
  {
    "date": "2026-06-26",
    "home_team": "Pittsburgh Pirates",
    "away_team": "Cincinnati Reds",
    "predicted_winner": "Pittsburgh Pirates",
    "win_probability": 0.6554072287290016,
    "model1_probability": 0.629590414774176,
    "model2_probability": 0.4675754099091063,
    "model3_probability": 0.5409436821937561,
    "ensemble_probability": 0.6554072287290016,
    "start_time_et": "2026-06-26 18:40:00 EDT",
    "start_time": "2026-06-26T18:40:00-04:00",
    "venue_name": "PNC Park",
    "day_night": "night",
    "model4_probability": 0.5828618206011774,
    "model5_probability": 0.6062658475818912,
    "model6_probability": 0.4879450500011444,
    "model7_probability": 0.6554072287290016,
    "model8_probability": 0.7583819944201864,
    "model9_probability": 0.5290248394012451,
    "model_rf_probability": 0.4988982121657812,
    "model_nn_probability": 0.014474973692536043,
    "model_svm_probability": 0.4796471124901335,
    "model_advanced_catboost_basic_probability": 0.4923763428529064,
    "model_advanced_catboost_probability": 0.36421579098722984,
    "model_advanced_lgbm_basic_probability": 0.4353481314652567,
    "model_advanced_lgbm_probability": 0.3821729019798787,
    "model_advanced_nn_probability": 0.06627848289974747,
    "model_advanced_rf_probability": 0.447393312238414,
    "model_advanced_svm_probability": 0.5133837821409224,
    "model_advanced_xgboost_basic_probability": 0.4882381856441498,
    "model_advanced_xgboost_probability": 0.513487696647644,
    "model1_extended_lgbm_probability": 0.4396160387493525,
    "model2_extended_catboost_probability": 0.44619026088623315,
    "model3_extended_xgboost_probability": 0.5747856497764587,
    "home_team_odds": -210.0,
    "home_team_probability_odds": 0.6774193548,
    "away_team_odds": 176.0,
    "away_team_probability_odds": 0.3623188406,
    "predicted_winner_odds": -210.0,
    "predicted_winner_probability_odds": 0.6774193548,
    "bookmaker": "fanduel",
    "bookmaker_title": "FanDuel"
  },
  {
    "date": "2026-06-26",
    "home_team": "Baltimore Orioles",
    "away_team": "Washington Nationals",
    "predicted_winner": "Washington Nationals",
    "win_probability": 0.09900191239555117,
    "model1_probability": 0.4032369401131341,
    "model2_probability": 0.5915722202280534,
    "model3_probability": 0.4297506809234619,
    "ensemble_probability": 0.09900191239555117,
    "start_time_et": "2026-06-26 19:05:00 EDT",
    "start_time": "2026-06-26T19:05:00-04:00",
    "venue_name": "Oriole Park at Camden Yards",
    "day_night": "night",
    "model4_probability": 0.16889336450871997,
    "model5_probability": 0.5214787364359232,
    "model6_probability": 0.4171931743621826,
    "model7_probability": 0.09900191239555117,
    "model8_probability": 0.6258362369851599,
    "model9_probability": 0.37465736269950867,
    "model_rf_probability": 0.5054366765376109,
    "model_nn_probability": 0.1765908456976648,
    "model_svm_probability": 0.54115103264673,
    "model_advanced_catboost_basic_probability": 0.6538941653866568,
    "model_advanced_catboost_probability": 0.6388405881603877,
    "model_advanced_lgbm_basic_probability": 0.607441526867927,
    "model_advanced_lgbm_probability": 0.6518104418920936,
    "model_advanced_nn_probability": 0.49179226865802556,
    "model_advanced_rf_probability": 0.5743164811339967,
    "model_advanced_svm_probability": 0.5133837821409224,
    "model_advanced_xgboost_basic_probability": 0.6217853426933289,
    "model_advanced_xgboost_probability": 0.593036949634552,
    "model1_extended_lgbm_probability": 0.4588833971350744,
    "model2_extended_catboost_probability": 0.5192384954404888,
    "model3_extended_xgboost_probability": 0.5220440626144409,
    "home_team_odds": -142.0,
    "home_team_probability_odds": 0.5867768595,
    "away_team_odds": 120.0,
    "away_team_probability_odds": 0.4545454545,
    "predicted_winner_odds": 120.0,
    "predicted_winner_probability_odds": 0.4545454545,
    "bookmaker": "fanduel",
    "bookmaker_title": "FanDuel"
  },
  {
    "date": "2026-06-26",
    "home_team": "Toronto Blue Jays",
    "away_team": "Texas Rangers",
    "predicted_winner": "Toronto Blue Jays",
    "win_probability": 0.9180683425045142,
    "model1_probability": 0.6349980314363526,
    "model2_probability": 0.6055073647138769,
    "model3_probability": 0.7553919553756714,
    "ensemble_probability": 0.9180683425045142,
    "start_time_et": "2026-06-26 19:07:00 EDT",
    "start_time": "2026-06-26T19:07:00-04:00",
    "venue_name": "Rogers Centre",
    "day_night": "night",
    "model4_probability": 0.7825696019264229,
    "model5_probability": 0.8051016656694001,
    "model6_probability": 0.8705312609672546,
    "model7_probability": 0.9180683425045142,
    "model8_probability": 0.660759629209785,
    "model9_probability": 0.801984965801239,
    "model_rf_probability": 0.5047775680030872,
    "model_nn_probability": 0.09967157166995469,
    "model_svm_probability": 0.491427449346967,
    "model_advanced_catboost_basic_probability": 0.38502360644845185,
    "model_advanced_catboost_probability": 0.2261001338003208,
    "model_advanced_lgbm_basic_probability": 0.3819570365692179,
    "model_advanced_lgbm_probability": 0.22329852214679993,
    "model_advanced_nn_probability": 0.018055603395433713,
    "model_advanced_rf_probability": 0.4045347282698645,
    "model_advanced_svm_probability": 0.5133837821409224,
    "model_advanced_xgboost_basic_probability": 0.2872307598590851,
    "model_advanced_xgboost_probability": 0.12330475449562073,
    "model1_extended_lgbm_probability": 0.32424847948138374,
    "model2_extended_catboost_probability": 0.384892444224333,
    "model3_extended_xgboost_probability": 0.2491757720708847,
    "home_team_odds": -104.0,
    "home_team_probability_odds": 0.5098039216,
    "away_team_odds": -112.0,
    "away_team_probability_odds": 0.5283018868,
    "predicted_winner_odds": -104.0,
    "predicted_winner_probability_odds": 0.5098039216,
    "bookmaker": "fanduel",
    "bookmaker_title": "FanDuel"
  },
  {
    "date": "2026-06-26",
    "home_team": "Cleveland Guardians",
    "away_team": "Seattle Mariners",
    "predicted_winner": "Cleveland Guardians",
    "win_probability": 0.9850827382021817,
    "model1_probability": 0.7638104458003199,
    "model2_probability": 0.7148474215558419,
    "model3_probability": 0.8247531652450562,
    "ensemble_probability": 0.9850827382021817,
    "start_time_et": "2026-06-26 19:10:00 EDT",
    "start_time": "2026-06-26T19:10:00-04:00",
    "venue_name": "Progressive Field",
    "day_night": "night",
    "model4_probability": 0.9498941393804252,
    "model5_probability": 0.8916015256339297,
    "model6_probability": 0.9106083512306213,
    "model7_probability": 0.9850827382021817,
    "model8_probability": 0.9616792264148836,
    "model9_probability": 0.8517875075340271,
    "model_rf_probability": 0.5656780415091229,
    "model_nn_probability": 0.011644356978231728,
    "model_svm_probability": 0.5278979393944689,
    "model_advanced_catboost_basic_probability": 0.5470115273301392,
    "model_advanced_catboost_probability": 0.6110209581820676,
    "model_advanced_lgbm_basic_probability": 0.6211797074132598,
    "model_advanced_lgbm_probability": 0.8014537295828766,
    "model_advanced_nn_probability": 0.9999913710017028,
    "model_advanced_rf_probability": 0.546488579813858,
    "model_advanced_svm_probability": 0.5133837821409224,
    "model_advanced_xgboost_basic_probability": 0.7042176723480225,
    "model_advanced_xgboost_probability": 0.8242409229278564,
    "model1_extended_lgbm_probability": 0.4914266937788064,
    "model2_extended_catboost_probability": 0.37413728568283044,
    "model3_extended_xgboost_probability": 0.5592601299285889,
    "home_team_odds": -112.0,
    "home_team_probability_odds": 0.5283018868,
    "away_team_odds": -104.0,
    "away_team_probability_odds": 0.5098039216,
    "predicted_winner_odds": -112.0,
    "predicted_winner_probability_odds": 0.5283018868,
    "bookmaker": "fanduel",
    "bookmaker_title": "FanDuel"
  },
  {
    "date": "2026-06-26",
    "home_team": "Tampa Bay Rays",
    "away_team": "Arizona Diamondbacks",
    "predicted_winner": "Arizona Diamondbacks",
    "win_probability": 0.3015439240379898,
    "model1_probability": 0.5386056101369623,
    "model2_probability": 0.4431315925529977,
    "model3_probability": 0.4859012961387634,
    "ensemble_probability": 0.3015439240379898,
    "start_time_et": "2026-06-26 19:10:00 EDT",
    "start_time": "2026-06-26T19:10:00-04:00",
    "venue_name": "Tropicana Field",
    "day_night": "night",
    "model4_probability": 0.5107676984185971,
    "model5_probability": 0.5025619475762927,
    "model6_probability": 0.44764262437820435,
    "model7_probability": 0.3015439240379898,
    "model8_probability": 0.47331486851143484,
    "model9_probability": 0.4892115294933319,
    "model_rf_probability": 0.4515674704976008,
    "model_nn_probability": 3.195274362506041e-06,
    "model_svm_probability": 0.4376129766820003,
    "model_advanced_catboost_basic_probability": 0.5820174868798236,
    "model_advanced_catboost_probability": 0.6606576650796497,
    "model_advanced_lgbm_basic_probability": 0.6253801905442883,
    "model_advanced_lgbm_probability": 0.6328322531045595,
    "model_advanced_nn_probability": 0.13677844476561135,
    "model_advanced_rf_probability": 0.5698976880010255,
    "model_advanced_svm_probability": 0.5133837821409224,
    "model_advanced_xgboost_basic_probability": 0.6146141290664673,
    "model_advanced_xgboost_probability": 0.5929189324378967,
    "model1_extended_lgbm_probability": 0.6485001783080776,
    "model2_extended_catboost_probability": 0.7080533673085582,
    "model3_extended_xgboost_probability": 0.6583197712898254,
    "home_team_odds": -136.0,
    "home_team_probability_odds": 0.5762711864,
    "away_team_odds": 116.0,
    "away_team_probability_odds": 0.462962963,
    "predicted_winner_odds": 116.0,
    "predicted_winner_probability_odds": 0.462962963,
    "bookmaker": "fanduel",
    "bookmaker_title": "FanDuel"
  },
  {
    "date": "2026-06-26",
    "home_team": "New York Mets",
    "away_team": "Philadelphia Phillies",
    "predicted_winner": "New York Mets",
    "win_probability": 0.8568659043434239,
    "model1_probability": 0.5554854449284774,
    "model2_probability": 0.6713706993462438,
    "model3_probability": 0.7288259863853455,
    "ensemble_probability": 0.8568659043434239,
    "start_time_et": "2026-06-26 19:10:00 EDT",
    "start_time": "2026-06-26T19:10:00-04:00",
    "venue_name": "Citi Field",
    "day_night": "night",
    "model4_probability": 0.7768141161779419,
    "model5_probability": 0.7272376795547082,
    "model6_probability": 0.8237466216087341,
    "model7_probability": 0.8568659043434239,
    "model8_probability": 0.7334667140341362,
    "model9_probability": 0.7036485075950623,
    "model_rf_probability": 0.5559493141750806,
    "model_nn_probability": 0.9999375775877241,
    "model_svm_probability": 0.5390520405673283,
    "model_advanced_catboost_basic_probability": 0.5921920821221398,
    "model_advanced_catboost_probability": 0.7275164262954741,
    "model_advanced_lgbm_basic_probability": 0.5525568711053382,
    "model_advanced_lgbm_probability": 0.5059434719200346,
    "model_advanced_nn_probability": 0.33876298142255185,
    "model_advanced_rf_probability": 0.5100622286052274,
    "model_advanced_svm_probability": 0.5133837821409224,
    "model_advanced_xgboost_basic_probability": 0.5112537145614624,
    "model_advanced_xgboost_probability": 0.6038963794708252,
    "model1_extended_lgbm_probability": 0.5662272619931114,
    "model2_extended_catboost_probability": 0.6163209015732946,
    "model3_extended_xgboost_probability": 0.5656194090843201,
    "home_team_odds": 132.0,
    "home_team_probability_odds": 0.4310344828,
    "away_team_odds": -156.0,
    "away_team_probability_odds": 0.609375,
    "predicted_winner_odds": 132.0,
    "predicted_winner_probability_odds": 0.4310344828,
    "bookmaker": "fanduel",
    "bookmaker_title": "FanDuel"
  },
  {
    "date": "2026-06-26",
    "home_team": "Boston Red Sox",
    "away_team": "New York Yankees",
    "predicted_winner": "Boston Red Sox",
    "win_probability": 0.8059345272311484,
    "model1_probability": 0.5412262145519704,
    "model2_probability": 0.4804726621827655,
    "model3_probability": 0.5115024447441101,
    "ensemble_probability": 0.8059345272311484,
    "start_time_et": "2026-06-26 19:10:00 EDT",
    "start_time": "2026-06-26T19:10:00-04:00",
    "venue_name": "Fenway Park",
    "day_night": "night",
    "model4_probability": 0.6611835949325757,
    "model5_probability": 0.5965078294029943,
    "model6_probability": 0.5751835703849792,
    "model7_probability": 0.8059345272311484,
    "model8_probability": 0.7236287393248998,
    "model9_probability": 0.5269145369529724,
    "model_rf_probability": 0.4829077168282173,
    "model_nn_probability": 0.9986866473753931,
    "model_svm_probability": 0.5491032714072202,
    "model_advanced_catboost_basic_probability": 0.4738215325362702,
    "model_advanced_catboost_probability": 0.48938700884367836,
    "model_advanced_lgbm_basic_probability": 0.4574446412740068,
    "model_advanced_lgbm_probability": 0.3814824001099285,
    "model_advanced_nn_probability": 5.541795117200399e-05,
    "model_advanced_rf_probability": 0.39975114575280496,
    "model_advanced_svm_probability": 0.5133837821409224,
    "model_advanced_xgboost_basic_probability": 0.39552074670791626,
    "model_advanced_xgboost_probability": 0.3720400035381317,
    "model1_extended_lgbm_probability": 0.3998682156028755,
    "model2_extended_catboost_probability": 0.40316894102005335,
    "model3_extended_xgboost_probability": 0.35518231987953186,
    "home_team_odds": -104.0,
    "home_team_probability_odds": 0.5098039216,
    "away_team_odds": -112.0,
    "away_team_probability_odds": 0.5283018868,
    "predicted_winner_odds": -104.0,
    "predicted_winner_probability_odds": 0.5098039216,
    "bookmaker": "fanduel",
    "bookmaker_title": "FanDuel"
  },
  {
    "date": "2026-06-26",
    "home_team": "Chicago White Sox",
    "away_team": "Kansas City Royals",
    "predicted_winner": "Chicago White Sox",
    "win_probability": 0.8606337627693786,
    "model1_probability": 0.4951523439408851,
    "model2_probability": 0.5231575201089854,
    "model3_probability": 0.5097532272338867,
    "ensemble_probability": 0.8606337627693786,
    "start_time_et": "2026-06-26 19:40:00 EDT",
    "start_time": "2026-06-26T19:40:00-04:00",
    "venue_name": "Rate Field",
    "day_night": "night",
    "model4_probability": 0.630798808138617,
    "model5_probability": 0.6970649591577128,
    "model6_probability": 0.5493374466896057,
    "model7_probability": 0.8606337627693786,
    "model8_probability": 0.5672301710475223,
    "model9_probability": 0.5841092467308044,
    "model_rf_probability": 0.4446349591020623,
    "model_nn_probability": 0.02865452733736588,
    "model_svm_probability": 0.4802789819227203,
    "model_advanced_catboost_basic_probability": 0.80278926134976,
    "model_advanced_catboost_probability": 0.9324799359948984,
    "model_advanced_lgbm_basic_probability": 0.6960466943478975,
    "model_advanced_lgbm_probability": 0.9392567136007943,
    "model_advanced_nn_probability": 0.9988756263846529,
    "model_advanced_rf_probability": 0.620587825002564,
    "model_advanced_svm_probability": 0.5133837821409224,
    "model_advanced_xgboost_basic_probability": 0.765471875667572,
    "model_advanced_xgboost_probability": 0.907579243183136,
    "model1_extended_lgbm_probability": 0.669484623524604,
    "model2_extended_catboost_probability": 0.7665565101750589,
    "model3_extended_xgboost_probability": 0.7940227389335632,
    "home_team_odds": -134.0,
    "home_team_probability_odds": 0.5726495726,
    "away_team_odds": 114.0,
    "away_team_probability_odds": 0.4672897196,
    "predicted_winner_odds": -134.0,
    "predicted_winner_probability_odds": 0.5726495726,
    "bookmaker": "fanduel",
    "bookmaker_title": "FanDuel"
  },
  {
    "date": "2026-06-26",
    "home_team": "Milwaukee Brewers",
    "away_team": "Chicago Cubs",
    "predicted_winner": "Milwaukee Brewers",
    "win_probability": 0.6999818383698965,
    "model1_probability": 0.6661138344707278,
    "model2_probability": 0.681966644777325,
    "model3_probability": 0.5590921640396118,
    "ensemble_probability": 0.6999818383698965,
    "start_time_et": "2026-06-26 19:45:00 EDT",
    "start_time": "2026-06-26T19:45:00-04:00",
    "venue_name": "American Family Field",
    "day_night": "night",
    "model4_probability": 0.788986453910476,
    "model5_probability": 0.7856539553634122,
    "model6_probability": 0.7291651368141174,
    "model7_probability": 0.6999818383698965,
    "model8_probability": 0.8159504981556536,
    "model9_probability": 0.6688235998153687,
    "model_rf_probability": 0.5818529946255844,
    "model_nn_probability": 0.11798276332754495,
    "model_svm_probability": 0.5272821614352489,
    "model_advanced_catboost_basic_probability": 0.44128263922904154,
    "model_advanced_catboost_probability": 0.1825611292139025,
    "model_advanced_lgbm_basic_probability": 0.48378089964292925,
    "model_advanced_lgbm_probability": 0.21337926517183645,
    "model_advanced_nn_probability": 1.0687013360996325e-06,
    "model_advanced_rf_probability": 0.42510487474285813,
    "model_advanced_svm_probability": 0.5133837821409224,
    "model_advanced_xgboost_basic_probability": 0.315945565700531,
    "model_advanced_xgboost_probability": 0.1354019194841385,
    "model1_extended_lgbm_probability": 0.48557780690599023,
    "model2_extended_catboost_probability": 0.4212853678751732,
    "model3_extended_xgboost_probability": 0.3016330897808075,
    "home_team_odds": -260.0,
    "home_team_probability_odds": 0.7222222222,
    "away_team_odds": 215.0,
    "away_team_probability_odds": 0.3174603175,
    "predicted_winner_odds": -260.0,
    "predicted_winner_probability_odds": 0.7222222222,
    "bookmaker": "fanduel",
    "bookmaker_title": "FanDuel"
  },
  {
    "date": "2026-06-26",
    "home_team": "Minnesota Twins",
    "away_team": "Colorado Rockies",
    "predicted_winner": "Minnesota Twins",
    "win_probability": 0.7172594419838956,
    "model1_probability": 0.4997238077469085,
    "model2_probability": 0.5178981822390566,
    "model3_probability": 0.5591140985488892,
    "ensemble_probability": 0.7172594419838956,
    "start_time_et": "2026-06-26 20:10:00 EDT",
    "start_time": "2026-06-26T20:10:00-04:00",
    "venue_name": "Target Field",
    "day_night": "night",
    "model4_probability": 0.7062478381772657,
    "model5_probability": 0.3888868334033628,
    "model6_probability": 0.6618338823318481,
    "model7_probability": 0.7172594419838956,
    "model8_probability": 0.42718900158522205,
    "model9_probability": 0.5861102938652039,
    "model_rf_probability": 0.45903675744762257,
    "model_nn_probability": 5.494870107763442e-06,
    "model_svm_probability": 0.5,
    "model_advanced_catboost_basic_probability": 0.6529097757382102,
    "model_advanced_catboost_probability": 0.7801253900026411,
    "model_advanced_lgbm_basic_probability": 0.6713159144658007,
    "model_advanced_lgbm_probability": 0.8482879183290697,
    "model_advanced_nn_probability": 0.9983210085578997,
    "model_advanced_rf_probability": 0.5440767860096469,
    "model_advanced_svm_probability": 0.5133837821409224,
    "model_advanced_xgboost_basic_probability": 0.6761009097099304,
    "model_advanced_xgboost_probability": 0.7736902236938477,
    "model1_extended_lgbm_probability": 0.7157644805673822,
    "model2_extended_catboost_probability": 0.5594608090855424,
    "model3_extended_xgboost_probability": 0.6586132645606995,
    "home_team_odds": -162.0,
    "home_team_probability_odds": 0.6183206107,
    "away_team_odds": 136.0,
    "away_team_probability_odds": 0.4237288136,
    "predicted_winner_odds": -162.0,
    "predicted_winner_probability_odds": 0.6183206107,
    "bookmaker": "fanduel",
    "bookmaker_title": "FanDuel"
  },
  {
    "date": "2026-06-26",
    "home_team": "St. Louis Cardinals",
    "away_team": "Miami Marlins",
    "predicted_winner": "Miami Marlins",
    "win_probability": 0.03208246823901939,
    "model1_probability": 0.3137559221770885,
    "model2_probability": 0.36128358056916615,
    "model3_probability": 0.27681615948677063,
    "ensemble_probability": 0.03208246823901939,
    "start_time_et": "2026-06-26 20:15:00 EDT",
    "start_time": "2026-06-26T20:15:00-04:00",
    "venue_name": "Busch Stadium",
    "day_night": "night",
    "model4_probability": 0.07978794106057113,
    "model5_probability": 0.5020063021986422,
    "model6_probability": 0.11097481846809387,
    "model7_probability": 0.03208246823901939,
    "model8_probability": 0.2570460826224409,
    "model9_probability": 0.23410780727863312,
    "model_rf_probability": 0.3817354293889945,
    "model_nn_probability": 1.146430715725287e-07,
    "model_svm_probability": 0.47763439040172956,
    "model_advanced_catboost_basic_probability": 0.551719158483982,
    "model_advanced_catboost_probability": 0.7428497750746819,
    "model_advanced_lgbm_basic_probability": 0.5480613618504125,
    "model_advanced_lgbm_probability": 0.7759298485414086,
    "model_advanced_nn_probability": 0.9970555043874371,
    "model_advanced_rf_probability": 0.48319447732571147,
    "model_advanced_svm_probability": 0.524515526555073,
    "model_advanced_xgboost_basic_probability": 0.6549971699714661,
    "model_advanced_xgboost_probability": 0.8242118954658508,
    "model1_extended_lgbm_probability": 0.513209471442474,
    "model2_extended_catboost_probability": 0.5170764640072673,
    "model3_extended_xgboost_probability": 0.5902069211006165,
    "home_team_odds": -116.0,
    "home_team_probability_odds": 0.537037037,
    "away_team_odds": -102.0,
    "away_team_probability_odds": 0.504950495,
    "predicted_winner_odds": -102.0,
    "predicted_winner_probability_odds": 0.504950495,
    "bookmaker": "fanduel",
    "bookmaker_title": "FanDuel"
  },
  {
    "date": "2026-06-26",
    "home_team": "Los Angeles Angels",
    "away_team": "Oakland Athletics",
    "predicted_winner": "Los Angeles Angels",
    "win_probability": 0.672630973744368,
    "model1_probability": 0.4685651425420549,
    "model2_probability": 0.6186506958892796,
    "model3_probability": 0.5475630760192871,
    "ensemble_probability": 0.672630973744368,
    "start_time_et": "2026-06-26 21:38:00 EDT",
    "start_time": "2026-06-26T21:38:00-04:00",
    "venue_name": "Angel Stadium",
    "day_night": "night",
    "model4_probability": 0.4844812553005483,
    "model5_probability": 0.5458429219865075,
    "model6_probability": 0.43511873483657837,
    "model7_probability": 0.672630973744368,
    "model8_probability": 0.5749448387794405,
    "model9_probability": 0.5007262229919434,
    "model_rf_probability": 0.535554489607662,
    "model_nn_probability": 0.46794677849893285,
    "model_svm_probability": 0.5,
    "model_advanced_catboost_basic_probability": 0.6689056921554742,
    "model_advanced_catboost_probability": 0.7433819274519596,
    "model_advanced_lgbm_basic_probability": 0.6332147686270654,
    "model_advanced_lgbm_probability": 0.45924650771510533,
    "model_advanced_nn_probability": 0.9999864291703643,
    "model_advanced_rf_probability": 0.5450375900178874,
    "model_advanced_svm_probability": 0.5133837821409224,
    "model_advanced_xgboost_basic_probability": 0.5739381909370422,
    "model_advanced_xgboost_probability": 0.4248014986515045,
    "model1_extended_lgbm_probability": 0.4517208379092998,
    "model2_extended_catboost_probability": 0.5427659366351503,
    "model3_extended_xgboost_probability": 0.5145643949508667,
    "home_team_odds": 108.0,
    "home_team_probability_odds": 0.4807692308,
    "away_team_odds": -126.0,
    "away_team_probability_odds": 0.5575221239,
    "predicted_winner_odds": 108.0,
    "predicted_winner_probability_odds": 0.4807692308,
    "bookmaker": "fanduel",
    "bookmaker_title": "FanDuel"
  },
  {
    "date": "2026-06-26",
    "home_team": "San Diego Padres",
    "away_team": "Los Angeles Dodgers",
    "predicted_winner": "San Diego Padres",
    "win_probability": 0.7409641916338008,
    "model1_probability": 0.5565596508639015,
    "model2_probability": 0.5156463939118963,
    "model3_probability": 0.47616979479789734,
    "ensemble_probability": 0.7409641916338008,
    "start_time_et": "2026-06-26 21:45:00 EDT",
    "start_time": "2026-06-26T21:45:00-04:00",
    "venue_name": "Petco Park",
    "day_night": "night",
    "model4_probability": 0.5527597910236605,
    "model5_probability": 0.6502863173183348,
    "model6_probability": 0.5532302260398865,
    "model7_probability": 0.7409641916338008,
    "model8_probability": 0.5459777510375488,
    "model9_probability": 0.5168670415878296,
    "model_rf_probability": 0.47772289988246297,
    "model_nn_probability": 0.9961637298077305,
    "model_svm_probability": 0.5228174821689157,
    "model_advanced_catboost_basic_probability": 0.5775108706167748,
    "model_advanced_catboost_probability": 0.6097980417106463,
    "model_advanced_lgbm_basic_probability": 0.5385314009236128,
    "model_advanced_lgbm_probability": 0.5865185650747898,
    "model_advanced_nn_probability": 0.9974548262304989,
    "model_advanced_rf_probability": 0.49395825346687094,
    "model_advanced_svm_probability": 0.5133837821409224,
    "model_advanced_xgboost_basic_probability": 0.4835349917411804,
    "model_advanced_xgboost_probability": 0.5685878396034241,
    "model1_extended_lgbm_probability": 0.4582282668430241,
    "model2_extended_catboost_probability": 0.4780175191412921,
    "model3_extended_xgboost_probability": 0.3621446192264557,
    "home_team_odds": 126.0,
    "home_team_probability_odds": 0.4424778761,
    "away_team_odds": -148.0,
    "away_team_probability_odds": 0.5967741935,
    "predicted_winner_odds": 126.0,
    "predicted_winner_probability_odds": 0.4424778761,
    "bookmaker": "fanduel",
    "bookmaker_title": "FanDuel"
  },
  {
    "date": "2026-06-26",
    "home_team": "San Francisco Giants",
    "away_team": "Atlanta Braves",
    "predicted_winner": "Atlanta Braves",
    "win_probability": 0.11328927573954546,
    "model1_probability": 0.38704674014215046,
    "model2_probability": 0.3827197517687033,
    "model3_probability": 0.4524625241756439,
    "ensemble_probability": 0.11328927573954546,
    "start_time_et": "2026-06-26 22:15:00 EDT",
    "start_time": "2026-06-26T22:15:00-04:00",
    "venue_name": "Oracle Park",
    "day_night": "night",
    "model4_probability": 0.3585418443139305,
    "model5_probability": 0.5211176869187247,
    "model6_probability": 0.4372449815273285,
    "model7_probability": 0.11328927573954546,
    "model8_probability": 0.3781882161891229,
    "model9_probability": 0.43701305985450745,
    "model_rf_probability": 0.3989539918540351,
    "model_nn_probability": 0.7973241453868561,
    "model_svm_probability": 0.4565536488215359,
    "model_advanced_catboost_basic_probability": 0.44450747463757073,
    "model_advanced_catboost_probability": 0.6798850268690606,
    "model_advanced_lgbm_basic_probability": 0.5282262933390307,
    "model_advanced_lgbm_probability": 0.6186009034560938,
    "model_advanced_nn_probability": 0.8309046500123698,
    "model_advanced_rf_probability": 0.4366992953944704,
    "model_advanced_svm_probability": 0.5133837821409224,
    "model_advanced_xgboost_basic_probability": 0.5173775553703308,
    "model_advanced_xgboost_probability": 0.5798479318618774,
    "model1_extended_lgbm_probability": 0.48068471037172544,
    "model2_extended_catboost_probability": 0.3938185056728094,
    "model3_extended_xgboost_probability": 0.436861127614975,
    "home_team_odds": -102.0,
    "home_team_probability_odds": 0.504950495,
    "away_team_odds": -116.0,
    "away_team_probability_odds": 0.537037037,
    "predicted_winner_odds": -116.0,
    "predicted_winner_probability_odds": 0.537037037,
    "bookmaker": "fanduel",
    "bookmaker_title": "FanDuel"
  },
  {
    "date": "2026-06-27",
    "home_team": "Detroit Tigers",
    "away_team": "Houston Astros",
    "predicted_winner": "Detroit Tigers",
    "win_probability": 0.7315967315022163,
    "model1_probability": 0.6395662206173945,
    "model2_probability": 0.7293940526090651,
    "model3_probability": 0.7167378067970276,
    "ensemble_probability": 0.7315967315022163,
    "start_time_et": "2026-06-27 13:10:00 EDT",
    "start_time": "2026-06-27T13:10:00-04:00",
    "venue_name": "Comerica Park",
    "day_night": "day",
    "model4_probability": 0.6488484886101719,
    "model5_probability": 0.8004440253423466,
    "model6_probability": 0.7971373796463013,
    "model7_probability": 0.7315967315022163,
    "model8_probability": 0.8742702500110018,
    "model9_probability": 0.7213405966758728,
    "model_rf_probability": 0.5902934500153351,
    "model_nn_probability": 0.9834091699628904,
    "model_svm_probability": 0.5446813796136662,
    "model_advanced_catboost_basic_probability": 0.6223387993030308,
    "model_advanced_catboost_probability": 0.5582284264305368,
    "model_advanced_lgbm_basic_probability": 0.5438951398472766,
    "model_advanced_lgbm_probability": 0.5347169058299618,
    "model_advanced_nn_probability": 0.007847480909761045,
    "model_advanced_rf_probability": 0.48731879121623956,
    "model_advanced_svm_probability": 0.5133837821409224,
    "model_advanced_xgboost_basic_probability": 0.5838121175765991,
    "model_advanced_xgboost_probability": 0.671692430973053,
    "model1_extended_lgbm_probability": 0.4826120487002264,
    "model2_extended_catboost_probability": 0.5528110588100588,
    "model3_extended_xgboost_probability": 0.6199519634246826,
    "home_team_odds": null,
    "home_team_probability_odds": null,
    "away_team_odds": null,
    "away_team_probability_odds": null,
    "predicted_winner_odds": null,
    "predicted_winner_probability_odds": null,
    "bookmaker": null,
    "bookmaker_title": null
  },
  {
    "date": "2026-06-27",
    "home_team": "Boston Red Sox",
    "away_team": "New York Yankees",
    "predicted_winner": "Boston Red Sox",
    "win_probability": 0.8278345745200829,
    "model1_probability": 0.5900628863463371,
    "model2_probability": 0.6043184057319448,
    "model3_probability": 0.5629728436470032,
    "ensemble_probability": 0.8278345745200829,
    "start_time_et": "2026-06-27 13:10:00 EDT",
    "start_time": "2026-06-27T13:10:00-04:00",
    "venue_name": "Fenway Park",
    "day_night": "day",
    "model4_probability": 0.72548896080557,
    "model5_probability": 0.6793314656553758,
    "model6_probability": 0.6346896290779114,
    "model7_probability": 0.8278345745200829,
    "model8_probability": 0.8225627395832531,
    "model9_probability": 0.5901885032653809,
    "model_rf_probability": 0.5132626374811398,
    "model_nn_probability": 0.9705018430014763,
    "model_svm_probability": 0.524017486224293,
    "model_advanced_catboost_basic_probability": 0.43630688375750665,
    "model_advanced_catboost_probability": 0.30892821145024746,
    "model_advanced_lgbm_basic_probability": 0.404362596192242,
    "model_advanced_lgbm_probability": 0.39620804856021397,
    "model_advanced_nn_probability": 0.01722000800488707,
    "model_advanced_rf_probability": 0.47459536157404125,
    "model_advanced_svm_probability": 0.5133837821409224,
    "model_advanced_xgboost_basic_probability": 0.3826392590999603,
    "model_advanced_xgboost_probability": 0.24664832651615143,
    "model1_extended_lgbm_probability": 0.3589016277581407,
    "model2_extended_catboost_probability": 0.451974284009538,
    "model3_extended_xgboost_probability": 0.308187872171402,
    "home_team_odds": null,
    "home_team_probability_odds": null,
    "away_team_odds": null,
    "away_team_probability_odds": null,
    "predicted_winner_odds": null,
    "predicted_winner_probability_odds": null,
    "bookmaker": null,
    "bookmaker_title": null
  },
  {
    "date": "2026-06-27",
    "home_team": "Toronto Blue Jays",
    "away_team": "Texas Rangers",
    "predicted_winner": "Toronto Blue Jays",
    "win_probability": 0.8774612296850756,
    "model1_probability": 0.6517299329728522,
    "model2_probability": 0.6492370592055744,
    "model3_probability": 0.7726917266845703,
    "ensemble_probability": 0.8774612296850756,
    "start_time_et": "2026-06-27 15:07:00 EDT",
    "start_time": "2026-06-27T15:07:00-04:00",
    "venue_name": "Rogers Centre",
    "day_night": "day",
    "model4_probability": 0.8128546794460612,
    "model5_probability": 0.7817033643838177,
    "model6_probability": 0.8498744368553162,
    "model7_probability": 0.8774612296850756,
    "model8_probability": 0.6460968731318237,
    "model9_probability": 0.8073186874389648,
    "model_rf_probability": 0.5380146043004934,
    "model_nn_probability": 0.0010858935903357723,
    "model_svm_probability": 0.46533520052529936,
    "model_advanced_catboost_basic_probability": 0.6305994698994699,
    "model_advanced_catboost_probability": 0.8293302225168443,
    "model_advanced_lgbm_basic_probability": 0.64040380585222,
    "model_advanced_lgbm_probability": 0.7659815248191653,
    "model_advanced_nn_probability": 0.9999995696988551,
    "model_advanced_rf_probability": 0.607631033344112,
    "model_advanced_svm_probability": 0.5133837821409224,
    "model_advanced_xgboost_basic_probability": 0.6729809641838074,
    "model_advanced_xgboost_probability": 0.6834569573402405,
    "model1_extended_lgbm_probability": 0.6727794357770362,
    "model2_extended_catboost_probability": 0.7132591901161095,
    "model3_extended_xgboost_probability": 0.6931951642036438,
    "home_team_odds": null,
    "home_team_probability_odds": null,
    "away_team_odds": null,
    "away_team_probability_odds": null,
    "predicted_winner_odds": null,
    "predicted_winner_probability_odds": null,
    "bookmaker": null,
    "bookmaker_title": null
  },
  {
    "date": "2026-06-27",
    "home_team": "Pittsburgh Pirates",
    "away_team": "Cincinnati Reds",
    "predicted_winner": "Pittsburgh Pirates",
    "win_probability": 0.7366135023353771,
    "model1_probability": 0.6624322612295857,
    "model2_probability": 0.4762355275445621,
    "model3_probability": 0.5623494982719421,
    "ensemble_probability": 0.7366135023353771,
    "start_time_et": "2026-06-27 16:05:00 EDT",
    "start_time": "2026-06-27T16:05:00-04:00",
    "venue_name": "PNC Park",
    "day_night": "day",
    "model4_probability": 0.6390697623928441,
    "model5_probability": 0.5149193705662751,
    "model6_probability": 0.519206702709198,
    "model7_probability": 0.7366135023353771,
    "model8_probability": 0.7096613128149166,
    "model9_probability": 0.5570868253707886,
    "model_rf_probability": 0.5384640160552469,
    "model_nn_probability": 3.4381787644729985e-06,
    "model_svm_probability": 0.47536719896255003,
    "model_advanced_catboost_basic_probability": 0.6481049014770927,
    "model_advanced_catboost_probability": 0.6455072093168807,
    "model_advanced_lgbm_basic_probability": 0.6463529799462542,
    "model_advanced_lgbm_probability": 0.8297155369255373,
    "model_advanced_nn_probability": 0.9999999999361675,
    "model_advanced_rf_probability": 0.570794193248172,
    "model_advanced_svm_probability": 0.5133837821409224,
    "model_advanced_xgboost_basic_probability": 0.7185078263282776,
    "model_advanced_xgboost_probability": 0.855505108833313,
    "model1_extended_lgbm_probability": 0.5156207290810272,
    "model2_extended_catboost_probability": 0.4737210137753191,
    "model3_extended_xgboost_probability": 0.5585519671440125,
    "home_team_odds": null,
    "home_team_probability_odds": null,
    "away_team_odds": null,
    "away_team_probability_odds": null,
    "predicted_winner_odds": null,
    "predicted_winner_probability_odds": null,
    "bookmaker": null,
    "bookmaker_title": null
  },
  {
    "date": "2026-06-27",
    "home_team": "New York Mets",
    "away_team": "Philadelphia Phillies",
    "predicted_winner": "New York Mets",
    "win_probability": 0.9107740577329784,
    "model1_probability": 0.5915808495901602,
    "model2_probability": 0.6731398420743122,
    "model3_probability": 0.7767333388328552,
    "ensemble_probability": 0.9107740577329784,
    "start_time_et": "2026-06-27 16:10:00 EDT",
    "start_time": "2026-06-27T16:10:00-04:00",
    "venue_name": "Citi Field",
    "day_night": "day",
    "model4_probability": 0.8432356881504456,
    "model5_probability": 0.783333790618109,
    "model6_probability": 0.7950764298439026,
    "model7_probability": 0.9107740577329784,
    "model8_probability": 0.7845821768898112,
    "model9_probability": 0.7527862191200256,
    "model_rf_probability": 0.6104398841627527,
    "model_nn_probability": 0.9999645937389331,
    "model_svm_probability": 0.5334968205935615,
    "model_advanced_catboost_basic_probability": 0.7245503808644335,
    "model_advanced_catboost_probability": 0.8551504190135699,
    "model_advanced_lgbm_basic_probability": 0.7134960369509874,
    "model_advanced_lgbm_probability": 0.8872116576313879,
    "model_advanced_nn_probability": 0.9996286046905419,
    "model_advanced_rf_probability": 0.6092112418456113,
    "model_advanced_svm_probability": 0.5133837821409224,
    "model_advanced_xgboost_basic_probability": 0.7381361722946167,
    "model_advanced_xgboost_probability": 0.84972083568573,
    "model1_extended_lgbm_probability": 0.7518926282427842,
    "model2_extended_catboost_probability": 0.6030905926120752,
    "model3_extended_xgboost_probability": 0.712936282157898,
    "home_team_odds": null,
    "home_team_probability_odds": null,
    "away_team_odds": null,
    "away_team_probability_odds": null,
    "predicted_winner_odds": null,
    "predicted_winner_probability_odds": null,
    "bookmaker": null,
    "bookmaker_title": null
  },
  {
    "date": "2026-06-27",
    "home_team": "Chicago White Sox",
    "away_team": "Kansas City Royals",
    "predicted_winner": "Chicago White Sox",
    "win_probability": 0.9058233411668797,
    "model1_probability": 0.5463458418749476,
    "model2_probability": 0.566830721402392,
    "model3_probability": 0.5478123426437378,
    "ensemble_probability": 0.9058233411668797,
    "start_time_et": "2026-06-27 16:10:00 EDT",
    "start_time": "2026-06-27T16:10:00-04:00",
    "venue_name": "Rate Field",
    "day_night": "day",
    "model4_probability": 0.6882285708556809,
    "model5_probability": 0.794494341702965,
    "model6_probability": 0.5595384240150452,
    "model7_probability": 0.9058233411668797,
    "model8_probability": 0.6723630277864339,
    "model9_probability": 0.6182321310043335,
    "model_rf_probability": 0.47819529916051395,
    "model_nn_probability": 0.005613776761985491,
    "model_svm_probability": 0.5,
    "model_advanced_catboost_basic_probability": 0.7324887371990937,
    "model_advanced_catboost_probability": 0.8085243819228004,
    "model_advanced_lgbm_basic_probability": 0.6583391543246093,
    "model_advanced_lgbm_probability": 0.5757954013845671,
    "model_advanced_nn_probability": 0.9999986854360728,
    "model_advanced_rf_probability": 0.5851457181171662,
    "model_advanced_svm_probability": 0.5133837821409224,
    "model_advanced_xgboost_basic_probability": 0.6482040286064148,
    "model_advanced_xgboost_probability": 0.5311286449432373,
    "model1_extended_lgbm_probability": 0.4970996485724948,
    "model2_extended_catboost_probability": 0.5957218743059784,
    "model3_extended_xgboost_probability": 0.5822643637657166,
    "home_team_odds": null,
    "home_team_probability_odds": null,
    "away_team_odds": null,
    "away_team_probability_odds": null,
    "predicted_winner_odds": null,
    "predicted_winner_probability_odds": null,
    "bookmaker": null,
    "bookmaker_title": null
  },
  {
    "date": "2026-06-27",
    "home_team": "Tampa Bay Rays",
    "away_team": "Arizona Diamondbacks",
    "predicted_winner": "Arizona Diamondbacks",
    "win_probability": 0.4327814602000323,
    "model1_probability": 0.5482075978071586,
    "model2_probability": 0.47887393796100924,
    "model3_probability": 0.5380584597587585,
    "ensemble_probability": 0.4327814602000323,
    "start_time_et": "2026-06-27 18:10:00 EDT",
    "start_time": "2026-06-27T18:10:00-04:00",
    "venue_name": "Tropicana Field",
    "day_night": "night",
    "model4_probability": 0.5815899093015138,
    "model5_probability": 0.6616245106782332,
    "model6_probability": 0.5293686985969543,
    "model7_probability": 0.4327814602000323,
    "model8_probability": 0.6048388177786713,
    "model9_probability": 0.5473579168319702,
    "model_rf_probability": 0.5062934526978111,
    "model_nn_probability": 3.9995935592801863e-08,
    "model_svm_probability": 0.49449166691317453,
    "model_advanced_catboost_basic_probability": 0.6998803876272077,
    "model_advanced_catboost_probability": 0.6526324196033688,
    "model_advanced_lgbm_basic_probability": 0.56565907515081,
    "model_advanced_lgbm_probability": 0.5357844556746033,
    "model_advanced_nn_probability": 0.9816688316034065,
    "model_advanced_rf_probability": 0.5280956704936288,
    "model_advanced_svm_probability": 0.5133837821409224,
    "model_advanced_xgboost_basic_probability": 0.5453324317932129,
    "model_advanced_xgboost_probability": 0.6050577163696289,
    "model1_extended_lgbm_probability": 0.49072988190268596,
    "model2_extended_catboost_probability": 0.5446379360691985,
    "model3_extended_xgboost_probability": 0.399154931306839,
    "home_team_odds": null,
    "home_team_probability_odds": null,
    "away_team_odds": null,
    "away_team_probability_odds": null,
    "predicted_winner_odds": null,
    "predicted_winner_probability_odds": null,
    "bookmaker": null,
    "bookmaker_title": null
  },
  {
    "date": "2026-06-27",
    "home_team": "Baltimore Orioles",
    "away_team": "Washington Nationals",
    "predicted_winner": "Washington Nationals",
    "win_probability": 0.11984390399094834,
    "model1_probability": 0.42629319807965527,
    "model2_probability": 0.6510896352174045,
    "model3_probability": 0.505730926990509,
    "ensemble_probability": 0.11984390399094834,
    "start_time_et": "2026-06-27 19:05:00 EDT",
    "start_time": "2026-06-27T19:05:00-04:00",
    "venue_name": "Oriole Park at Camden Yards",
    "day_night": "night",
    "model4_probability": 0.1991806698827216,
    "model5_probability": 0.6624378975532724,
    "model6_probability": 0.4217124581336975,
    "model7_probability": 0.11984390399094834,
    "model8_probability": 0.7981396656965127,
    "model9_probability": 0.4231049418449402,
    "model_rf_probability": 0.5392812118550847,
    "model_nn_probability": 0.02959388153311122,
    "model_svm_probability": 0.52945619851393,
    "model_advanced_catboost_basic_probability": 0.6380004429562184,
    "model_advanced_catboost_probability": 0.8086899915981176,
    "model_advanced_lgbm_basic_probability": 0.5834416536927703,
    "model_advanced_lgbm_probability": 0.5866680971134359,
    "model_advanced_nn_probability": 0.999996188983691,
    "model_advanced_rf_probability": 0.523669998574217,
    "model_advanced_svm_probability": 0.5133837821409224,
    "model_advanced_xgboost_basic_probability": 0.5556922554969788,
    "model_advanced_xgboost_probability": 0.6600242853164673,
    "model1_extended_lgbm_probability": 0.591331052356518,
    "model2_extended_catboost_probability": 0.6306171985558399,
    "model3_extended_xgboost_probability": 0.5589768290519714,
    "home_team_odds": null,
    "home_team_probability_odds": null,
    "away_team_odds": null,
    "away_team_probability_odds": null,
    "predicted_winner_odds": null,
    "predicted_winner_probability_odds": null,
    "bookmaker": null,
    "bookmaker_title": null
  },
  {
    "date": "2026-06-27",
    "home_team": "Minnesota Twins",
    "away_team": "Colorado Rockies",
    "predicted_winner": "Minnesota Twins",
    "win_probability": 0.7616206608737589,
    "model1_probability": 0.5258597403880294,
    "model2_probability": 0.5439138939288104,
    "model3_probability": 0.565069854259491,
    "ensemble_probability": 0.7616206608737589,
    "start_time_et": "2026-06-27 19:10:00 EDT",
    "start_time": "2026-06-27T19:10:00-04:00",
    "venue_name": "Target Field",
    "day_night": "night",
    "model4_probability": 0.7177559570052858,
    "model5_probability": 0.3846942953389134,
    "model6_probability": 0.6507696509361267,
    "model7_probability": 0.7616206608737589,
    "model8_probability": 0.4060114282782113,
    "model9_probability": 0.5933708548545837,
    "model_rf_probability": 0.4751631148453126,
    "model_nn_probability": 3.948057819493402e-07,
    "model_svm_probability": 0.5088833034245319,
    "model_advanced_catboost_basic_probability": 0.5893974113445396,
    "model_advanced_catboost_probability": 0.83133929660232,
    "model_advanced_lgbm_basic_probability": 0.5877062755606934,
    "model_advanced_lgbm_probability": 0.8340306504867234,
    "model_advanced_nn_probability": 0.9914116611231887,
    "model_advanced_rf_probability": 0.5500226200524514,
    "model_advanced_svm_probability": 0.524515526555073,
    "model_advanced_xgboost_basic_probability": 0.7040266990661621,
    "model_advanced_xgboost_probability": 0.862096905708313,
    "model1_extended_lgbm_probability": 0.5411696380361324,
    "model2_extended_catboost_probability": 0.5192164603960123,
    "model3_extended_xgboost_probability": 0.6112719178199768,
    "home_team_odds": null,
    "home_team_probability_odds": null,
    "away_team_odds": null,
    "away_team_probability_odds": null,
    "predicted_winner_odds": null,
    "predicted_winner_probability_odds": null,
    "bookmaker": null,
    "bookmaker_title": null
  },
  {
    "date": "2026-06-27",
    "home_team": "Milwaukee Brewers",
    "away_team": "Chicago Cubs",
    "predicted_winner": "Milwaukee Brewers",
    "win_probability": 0.6775235489766313,
    "model1_probability": 0.6871774524216793,
    "model2_probability": 0.7374748077135769,
    "model3_probability": 0.5993648767471313,
    "ensemble_probability": 0.6775235489766313,
    "start_time_et": "2026-06-27 19:10:00 EDT",
    "start_time": "2026-06-27T19:10:00-04:00",
    "venue_name": "American Family Field",
    "day_night": "night",
    "model4_probability": 0.7976732984406715,
    "model5_probability": 0.8250175547631451,
    "model6_probability": 0.7505820393562317,
    "model7_probability": 0.6775235489766313,
    "model8_probability": 0.8493017664220619,
    "model9_probability": 0.6909273862838745,
    "model_rf_probability": 0.604747783348627,
    "model_nn_probability": 0.9957287957749906,
    "model_svm_probability": 0.5442944363766952,
    "model_advanced_catboost_basic_probability": 0.48022340917160483,
    "model_advanced_catboost_probability": 0.7580432609100148,
    "model_advanced_lgbm_basic_probability": 0.5696052516345173,
    "model_advanced_lgbm_probability": 0.6495775149803141,
    "model_advanced_nn_probability": 0.5741888825741404,
    "model_advanced_rf_probability": 0.5042027833115803,
    "model_advanced_svm_probability": 0.5133837821409224,
    "model_advanced_xgboost_basic_probability": 0.5653062462806702,
    "model_advanced_xgboost_probability": 0.6211265921592712,
    "model1_extended_lgbm_probability": 0.5185629466164303,
    "model2_extended_catboost_probability": 0.43508625274182317,
    "model3_extended_xgboost_probability": 0.46580174565315247,
    "home_team_odds": null,
    "home_team_probability_odds": null,
    "away_team_odds": null,
    "away_team_probability_odds": null,
    "predicted_winner_odds": null,
    "predicted_winner_probability_odds": null,
    "bookmaker": null,
    "bookmaker_title": null
  },
  {
    "date": "2026-06-27",
    "home_team": "Cleveland Guardians",
    "away_team": "Seattle Mariners",
    "predicted_winner": "Cleveland Guardians",
    "win_probability": 0.9869080018451765,
    "model1_probability": 0.7806271810794029,
    "model2_probability": 0.7475258627962037,
    "model3_probability": 0.8630436062812805,
    "ensemble_probability": 0.9869080018451765,
    "start_time_et": "2026-06-27 19:10:00 EDT",
    "start_time": "2026-06-27T19:10:00-04:00",
    "venue_name": "Progressive Field",
    "day_night": "night",
    "model4_probability": 0.9676720717652787,
    "model5_probability": 0.9183069468627462,
    "model6_probability": 0.9189319610595703,
    "model7_probability": 0.9869080018451765,
    "model8_probability": 0.9731505027959209,
    "model9_probability": 0.8873801827430725,
    "model_rf_probability": 0.6099635710978563,
    "model_nn_probability": 0.03934792672055096,
    "model_svm_probability": 0.5204991685871664,
    "model_advanced_catboost_basic_probability": 0.8261954816074397,
    "model_advanced_catboost_probability": 0.9437722643925012,
    "model_advanced_lgbm_basic_probability": 0.7291638950467294,
    "model_advanced_lgbm_probability": 0.9606999444050843,
    "model_advanced_nn_probability": 0.9968073139339169,
    "model_advanced_rf_probability": 0.6598890209686977,
    "model_advanced_svm_probability": 0.5133837821409224,
    "model_advanced_xgboost_basic_probability": 0.7877209782600403,
    "model_advanced_xgboost_probability": 0.932120680809021,
    "model1_extended_lgbm_probability": 0.6991944494938855,
    "model2_extended_catboost_probability": 0.7559020300209555,
    "model3_extended_xgboost_probability": 0.8229596614837646,
    "home_team_odds": null,
    "home_team_probability_odds": null,
    "away_team_odds": null,
    "away_team_probability_odds": null,
    "predicted_winner_odds": null,
    "predicted_winner_probability_odds": null,
    "bookmaker": null,
    "bookmaker_title": null
  },
  {
    "date": "2026-06-27",
    "home_team": "St. Louis Cardinals",
    "away_team": "Miami Marlins",
    "predicted_winner": "Miami Marlins",
    "win_probability": 0.05305910250938031,
    "model1_probability": 0.3894926293183241,
    "model2_probability": 0.4255364052566467,
    "model3_probability": 0.3241397738456726,
    "ensemble_probability": 0.05305910250938031,
    "start_time_et": "2026-06-27 19:15:00 EDT",
    "start_time": "2026-06-27T19:15:00-04:00",
    "venue_name": "Busch Stadium",
    "day_night": "night",
    "model4_probability": 0.1190791648021567,
    "model5_probability": 0.5736219930808204,
    "model6_probability": 0.14735247194766998,
    "model7_probability": 0.05305910250938031,
    "model8_probability": 0.3422388614190482,
    "model9_probability": 0.2936689257621765,
    "model_rf_probability": 0.43907220823146303,
    "model_nn_probability": 3.177130839760546e-08,
    "model_svm_probability": 0.5,
    "model_advanced_catboost_basic_probability": 0.6236460601463272,
    "model_advanced_catboost_probability": 0.8229788873081391,
    "model_advanced_lgbm_basic_probability": 0.7611289632362,
    "model_advanced_lgbm_probability": 0.9052340102511702,
    "model_advanced_nn_probability": 0.999999986260814,
    "model_advanced_rf_probability": 0.6102917700279413,
    "model_advanced_svm_probability": 0.5133837821409224,
    "model_advanced_xgboost_basic_probability": 0.7954586148262024,
    "model_advanced_xgboost_probability": 0.9133290648460388,
    "model1_extended_lgbm_probability": 0.6164049261144054,
    "model2_extended_catboost_probability": 0.6471422015687525,
    "model3_extended_xgboost_probability": 0.850670337677002,
    "home_team_odds": null,
    "home_team_probability_odds": null,
    "away_team_odds": null,
    "away_team_probability_odds": null,
    "predicted_winner_odds": null,
    "predicted_winner_probability_odds": null,
    "bookmaker": null,
    "bookmaker_title": null
  },
  {
    "date": "2026-06-27",
    "home_team": "San Diego Padres",
    "away_team": "Los Angeles Dodgers",
    "predicted_winner": "San Diego Padres",
    "win_probability": 0.8186685500927322,
    "model1_probability": 0.5964387837381365,
    "model2_probability": 0.5820506713310862,
    "model3_probability": 0.5176157355308533,
    "ensemble_probability": 0.8186685500927322,
    "start_time_et": "2026-06-27 20:40:00 EDT",
    "start_time": "2026-06-27T20:40:00-04:00",
    "venue_name": "Petco Park",
    "day_night": "night",
    "model4_probability": 0.6289049130174305,
    "model5_probability": 0.6865852515043959,
    "model6_probability": 0.5887105464935303,
    "model7_probability": 0.8186685500927322,
    "model8_probability": 0.6961266829421299,
    "model9_probability": 0.580560028553009,
    "model_rf_probability": 0.46269368186069637,
    "model_nn_probability": 0.9773610564066452,
    "model_svm_probability": 0.5274808418434624,
    "model_advanced_catboost_basic_probability": 0.5663952143046411,
    "model_advanced_catboost_probability": 0.5713297203356459,
    "model_advanced_lgbm_basic_probability": 0.5052089766526994,
    "model_advanced_lgbm_probability": 0.3702710462783254,
    "model_advanced_nn_probability": 0.0026959855532355226,
    "model_advanced_rf_probability": 0.4646592402416402,
    "model_advanced_svm_probability": 0.5133837821409224,
    "model_advanced_xgboost_basic_probability": 0.4659033715724945,
    "model_advanced_xgboost_probability": 0.38003912568092346,
    "model1_extended_lgbm_probability": 0.45407221880810966,
    "model2_extended_catboost_probability": 0.45793269822277494,
    "model3_extended_xgboost_probability": 0.3965904116630554,
    "home_team_odds": null,
    "home_team_probability_odds": null,
    "away_team_odds": null,
    "away_team_probability_odds": null,
    "predicted_winner_odds": null,
    "predicted_winner_probability_odds": null,
    "bookmaker": null,
    "bookmaker_title": null
  },
  {
    "date": "2026-06-27",
    "home_team": "San Francisco Giants",
    "away_team": "Atlanta Braves",
    "predicted_winner": "Atlanta Braves",
    "win_probability": 0.16396992438371066,
    "model1_probability": 0.43523208530656626,
    "model2_probability": 0.477960704161497,
    "model3_probability": 0.5079957246780396,
    "ensemble_probability": 0.16396992438371066,
    "start_time_et": "2026-06-27 21:05:00 EDT",
    "start_time": "2026-06-27T21:05:00-04:00",
    "venue_name": "Oracle Park",
    "day_night": "night",
    "model4_probability": 0.4231843938762058,
    "model5_probability": 0.6532519073695385,
    "model6_probability": 0.4681602716445923,
    "model7_probability": 0.16396992438371066,
    "model8_probability": 0.4938794904073843,
    "model9_probability": 0.5068185329437256,
    "model_rf_probability": 0.43596718359165965,
    "model_nn_probability": 0.012513956315467572,
    "model_svm_probability": 0.47715757222784744,
    "model_advanced_catboost_basic_probability": 0.5146402110774255,
    "model_advanced_catboost_probability": 0.38113608136218646,
    "model_advanced_lgbm_basic_probability": 0.4928434665519099,
    "model_advanced_lgbm_probability": 0.5235544607392041,
    "model_advanced_nn_probability": 0.004085647787910633,
    "model_advanced_rf_probability": 0.534588657326283,
    "model_advanced_svm_probability": 0.5133837821409224,
    "model_advanced_xgboost_basic_probability": 0.40317603945732117,
    "model_advanced_xgboost_probability": 0.3247499465942383,
    "model1_extended_lgbm_probability": 0.535795422619848,
    "model2_extended_catboost_probability": 0.47936541799402055,
    "model3_extended_xgboost_probability": 0.41818270087242126,
    "home_team_odds": null,
    "home_team_probability_odds": null,
    "away_team_odds": null,
    "away_team_probability_odds": null,
    "predicted_winner_odds": null,
    "predicted_winner_probability_odds": null,
    "bookmaker": null,
    "bookmaker_title": null
  },
  {
    "date": "2026-06-27",
    "home_team": "Los Angeles Angels",
    "away_team": "Oakland Athletics",
    "predicted_winner": "Los Angeles Angels",
    "win_probability": 0.7207040744323757,
    "model1_probability": 0.5011294738288642,
    "model2_probability": 0.6832939349906438,
    "model3_probability": 0.5928899645805359,
    "ensemble_probability": 0.7207040744323757,
    "start_time_et": "2026-06-27 21:38:00 EDT",
    "start_time": "2026-06-27T21:38:00-04:00",
    "venue_name": "Angel Stadium",
    "day_night": "night",
    "model4_probability": 0.5439767313202551,
    "model5_probability": 0.6607729056205857,
    "model6_probability": 0.4571479260921478,
    "model7_probability": 0.7207040744323757,
    "model8_probability": 0.7540393465844403,
    "model9_probability": 0.5418989062309265,
    "model_rf_probability": 0.5642920420053648,
    "model_nn_probability": 0.9833469907454814,
    "model_svm_probability": 0.5108166565046801,
    "model_advanced_catboost_basic_probability": 0.7533351886313953,
    "model_advanced_catboost_probability": 0.7475963684949228,
    "model_advanced_lgbm_basic_probability": 0.629827148713557,
    "model_advanced_lgbm_probability": 0.6460004469994732,
    "model_advanced_nn_probability": 0.6925323750495389,
    "model_advanced_rf_probability": 0.614688160268396,
    "model_advanced_svm_probability": 0.5133837821409224,
    "model_advanced_xgboost_basic_probability": 0.662304162979126,
    "model_advanced_xgboost_probability": 0.6428714990615845,
    "model1_extended_lgbm_probability": 0.5196331399524893,
    "model2_extended_catboost_probability": 0.6039604492740016,
    "model3_extended_xgboost_probability": 0.5712753534317017,
    "home_team_odds": null,
    "home_team_probability_odds": null,
    "away_team_odds": null,
    "away_team_probability_odds": null,
    "predicted_winner_odds": null,
    "predicted_winner_probability_odds": null,
    "bookmaker": null,
    "bookmaker_title": null
  }
]